{
  "a-drop-of-pencil-s": {
    "unsplash": {
      "id": "oVucl-WfQCM",
      "downloads": 126,
      "likes": 0,
      "views": 6152
    },
    "flickr": {
      "id": "16249484066",
      "favs": 324
    }
  },
  "a-storm-is-coming": {
    "pixelfed": "457651097645319734",
    "locationscout": "kenya/34386-green-valleys-after-the-rain-maasai-mara-national-reserve/80559",
    "flickr": {
      "id": "51032576491",
      "favs": 76
    }
  },
  "a-view-from-the-hong-kong-avenue-of-stars": {
    "locationscout": "hong-kong/1623-hong-kong-avenue-of-stars/2720",
    "flickr": {
      "id": "51642604480",
      "favs": 65
    }
  },
  "an-evening-at-chateau-de-chambord": {
    "pixelfed": "358302282417507300",
    "flickr": {
      "id": "51622495641",
      "favs": 188
    }
  },
  "bacchus-dream": {
    "unsplash": {
      "id": "yHF4cpD3hmw",
      "downloads": 120,
      "likes": 0,
      "views": 6671
    },
    "flickr": {
      "id": "4303250759",
      "favs": 3
    }
  },
  "beautiful-maasai-giraffe": {
    "pixelfed": "458914864570067261",
    "flickr": {
      "id": "50714492792",
      "favs": 87
    }
  },
  "betlemi-street-stairs": {
    "pixelfed": "408017288080816124",
    "flickr": {
      "id": "51895078837",
      "favs": 63
    }
  },
  "biohazard": {
    "pixelfed": "398032990910661309",
    "flickr": {
      "id": "51876943006",
      "favs": 70
    }
  },
  "blue-hotel": {
    "pixelfed": "306834878987636736",
    "flickr": {
      "id": "49798845563",
      "favs": 113
    }
  },
  "blue-house-and-other-colors": {
    "locationscout": "hong-kong/6935-blue-house-and-other-colorful-buildings/12699",
    "flickr": {
      "id": "31096954012",
      "favs": 31
    }
  },
  "bonjour": {
    "unsplash": {
      "id": "om3kEa7YpRg",
      "downloads": 2983,
      "likes": 0,
      "views": 230564
    },
    "flickr": {
      "id": "28886920106",
      "favs": 70
    }
  },
  "brooklyn-bridge-web-of-cables": {
    "locationscout": "usa/1-brooklyn-bridge-new-york-city/15435",
    "flickr": {
      "id": "23057719463",
      "favs": 50
    }
  },
  "chreli-abano": {
    "pixelfed": "408020148449069125",
    "flickr": {
      "id": "51932567099",
      "favs": 33
    }
  },
  "color-patches": {
    "unsplash": {
      "id": "i9ST_o_oaJ0",
      "downloads": 1152,
      "likes": 0,
      "views": 335608
    },
    "flickr": {
      "id": "39177187902",
      "favs": 45
    }
  },
  "colors-of-little-italy": {
    "pixelfed": "2582",
    "unsplash": {
      "id": "7GDh_WBknxU",
      "downloads": 4062,
      "likes": 0,
      "views": 766590
    },
    "flickr": {
      "id": "41779681045",
      "favs": 97
    }
  },
  "colourful-netherlands": {
    "unsplash": {
      "id": "0jj1xNsSOBo",
      "downloads": 1054,
      "likes": 0,
      "views": 69259
    },
    "locationscout": "netherlands/6936-colorful-houses-in-groningen-the-netherlands/12700",
    "flickr": {
      "id": "20526424273",
      "favs": 421
    }
  },
  "curious-red-deer-in-espace-rambouillet": {
    "pixelfed": "391335673001054675",
    "flickr": {
      "id": "51645170594",
      "favs": 52
    }
  },
  "don-t-fear-the-light": {
    "unsplash": {
      "id": "AJrYClJujhI",
      "downloads": 102,
      "likes": 0,
      "views": 10395
    },
    "flickr": {
      "id": "2704862",
      "favs": 242
    }
  },
  "double-helix": {
    "flickr": {
      "id": "36060657345",
      "favs": 625
    },
    "unsplash": {
      "id": "z3v__zzp22U",
      "downloads": 14032,
      "likes": 0,
      "views": 1632934
    },
    "locationscout": "italy/6458-vatican-museum-spiral-staircase-rome/16235"
  },
  "drinking-water-does-not-reach-the-tap": {
    "pixelfed": "286582956850548736",
    "flickr": {
      "id": "51093729559",
      "favs": 13
    }
  },
  "driving-south": {
    "pixelfed": "2670",
    "flickr": {
      "id": "19001854351",
      "favs": 65
    }
  },
  "eilean-donan-castle": {
    "locationscout": "united-kingdom/4446-eilean-donan-castle/98195",
    "flickr": {
      "id": "32380566763",
      "favs": 65
    }
  },
  "elephant-in-maasai-mara": {
    "pixelfed": "286545853164949504",
    "flickr": {
      "id": "49799700847",
      "favs": 147
    }
  },
  "elephants-grazing-in-amboseli-swamps": {
    "pixelfed": "106012324078424064",
    "flickr": {
      "id": "48737686858",
      "favs": 156
    }
  },
  "eletricos-de-lisboa": {
    "pixelfed": "4899",
    "flickr": {
      "id": "29763446663",
      "favs": 25
    }
  },
  "faded-blue": {
    "pixelfed": "416249825699732726",
    "flickr": {
      "id": "51978460142",
      "favs": 44
    }
  },
  "find-your-way": {
    "unsplash": {
      "id": "-Swg3jOJD8o",
      "downloads": 7161,
      "likes": 0,
      "views": 1143368
    },
    "flickr": {
      "id": "23866042168",
      "favs": 73
    }
  },
  "flooded-gate-at-lake-nakuru": {
    "pixelfed": "319854894028820480",
    "flickr": {
      "id": "51109697626",
      "favs": 47
    }
  },
  "fluorescent-jellyfishes": {
    "unsplash": {
      "id": "9pgXE54mO8A",
      "downloads": 95,
      "likes": 0,
      "views": 7224
    },
    "flickr": {
      "id": "2632478734",
      "favs": 383
    }
  },
  "gondola-lift-to-narikala-fortress": {
    "pixelfed": "408016626777204709",
    "flickr": {
      "id": "51893126779",
      "favs": 39
    }
  },
  "grant-s-zebra": {
    "pixelfed": "457650017687057932",
    "flickr": {
      "id": "49798845388",
      "favs": 87
    }
  },
  "holy-trinity-cathedral-of-tbilisi": {
    "pixelfed": "445208889974375805",
    "flickr": {
      "id": "51935995334",
      "favs": 89
    }
  },
  "hong-kong-planet": {
    "unsplash": {
      "id": "fuopjgwxacA",
      "downloads": 69,
      "likes": 0,
      "views": 4064
    },
    "flickr": {
      "id": "21485169051",
      "favs": 15
    }
  },
  "ice-shards": {
    "unsplash": {
      "id": "u7r80XS7KoA",
      "downloads": 5854,
      "likes": 0,
      "views": 472178
    },
    "flickr": {
      "id": "51150387781",
      "favs": 60
    }
  },
  "imeri-gramvousa": {
    "pixelfed": "15936",
    "flickr": {
      "id": "45226341342",
      "favs": 167
    }
  },
  "in-the-starting-blocks-for-the-men-s-110m-hurdles": {
    "unsplash": {
      "id": "-4trKf0Kbow",
      "downloads": 67763,
      "likes": 0,
      "views": 8825313
    },
    "flickr": {
      "id": "28286280058",
      "favs": 10
    }
  },
  "incense-coils-in-man-mo-temple-hong-kong": {
    "unsplash": {
      "id": "hfIMkIcIq_k",
      "downloads": 8472,
      "likes": 0,
      "views": 2482785
    },
    "locationscout": "hong-kong/1603-man-mo-temple-in-sheung-wan-on-hong-kong-island/2697",
    "flickr": {
      "id": "20662401815",
      "favs": 37
    }
  },
  "julie": {
    "unsplash": {
      "id": "dTJCyPC5bvc",
      "downloads": 2160,
      "likes": 0,
      "views": 343937
    },
    "flickr": {
      "id": "33702537825",
      "favs": 93
    }
  },
  "kaleidoscope-house": {
    "pixelfed": "408018153730041874",
    "flickr": {
      "id": "51898403739",
      "favs": 60
    }
  },
  "koezio-labyrinth": {
    "unsplash": {
      "id": "sfWsQ9Ch5ZU",
      "downloads": 82,
      "likes": 0,
      "views": 7851
    },
    "flickr": {
      "id": "52626150856",
      "favs": 34
    }
  },
  "la-demoiselle-du-quai-des-dames": {
    "unsplash": {
      "id": "vh5bb0e1JSU",
      "downloads": 89,
      "likes": 0,
      "views": 4681
    },
    "flickr": {
      "id": "35055194181",
      "favs": 30
    }
  },
  "la-mere-rouge": {
    "flickr": {
      "id": "3921511",
      "favs": 107
    }
  },
  "le-petit-poucet": {
    "unsplash": {
      "id": "yBNIf_ny6Ro",
      "downloads": 11571,
      "likes": 0,
      "views": 1583262
    },
    "flickr": {
      "id": "26041704998",
      "favs": 45
    }
  },
  "let-s-go-for-a-ride": {
    "unsplash": {
      "id": "14SPxCoVgi4",
      "downloads": 3821,
      "likes": 0,
      "views": 841431
    },
    "flickr": {
      "id": "44478435995",
      "favs": 125
    }
  },
  "let-s-ride": {
    "locationscout": "netherlands/6937-madurodam-a-miniature-park-of-dutch-landmarks/12701",
    "flickr": {
      "id": "6021112656",
      "favs": 7
    }
  },
  "light-rays": {
    "pixelfed": "391334867077145004",
    "flickr": {
      "id": "51644515886",
      "favs": 141
    }
  },
  "long-strides": {
    "unsplash": {
      "id": "poa-Ycw1W8U",
      "downloads": 32460,
      "likes": 0,
      "views": 4794745
    },
    "flickr": {
      "id": "28286278428",
      "favs": 9
    }
  },
  "lumberjacks": {
    "pixelfed": "398113696427559274",
    "flickr": {
      "id": "51877200256",
      "favs": 54
    }
  },
  "magmatic-eruption": {
    "pixelfed": "399340944708979167",
    "flickr": {
      "id": "51881613786",
      "favs": 68
    }
  },
  "majestic-kilimanjaro": {
    "pixelfed": "157784506319900672",
    "flickr": {
      "id": "48929589476",
      "favs": 112
    }
  },
  "mtatsminda-view-point-over-tbilisi": {
    "pixelfed": "416250264134794496",
    "flickr": {
      "id": "51979466046",
      "favs": 55
    }
  },
  "new-york-lovers": {
    "locationscout": "usa/1419-wall-painting/2428",
    "flickr": {
      "id": "20132185481",
      "favs": 23
    }
  },
  "not-so-colourful-netherlands": {
    "unsplash": {
      "id": "nF6VjdYUsvQ",
      "downloads": 106,
      "likes": 0,
      "views": 4660
    },
    "locationscout": "netherlands/6936-colorful-houses-in-groningen-the-netherlands/16234",
    "flickr": {
      "id": "33545073172",
      "favs": 238
    }
  },
  "old-wooden-house-atmosphere": {
    "pixelfed": "408018817130362919",
    "flickr": {
      "id": "51900900785",
      "favs": 39
    }
  },
  "overlooking-tbilisi": {
    "pixelfed": "402254683518118192",
    "flickr": {
      "id": "51891943088",
      "favs": 43
    }
  },
  "palazzo-cavalli-franchetti": {
    "unsplash": {
      "id": "WWHwaxBa9YA",
      "downloads": 2491,
      "likes": 0,
      "views": 448957
    },
    "flickr": {
      "id": "32112317926",
      "favs": 46
    }
  },
  "phare-des-baleines": {
    "unsplash": {
      "id": "VU8HxMAP79U",
      "downloads": 3340,
      "likes": 0,
      "views": 300891
    },
    "flickr": {
      "id": "36356885164",
      "favs": 194
    }
  },
  "pigments": {
    "unsplash": {
      "id": "dysl7LZ7bSM",
      "downloads": 1242,
      "likes": 0,
      "views": 241096
    },
    "flickr": {
      "id": "18907163221",
      "favs": 25
    }
  },
  "playa-moron": {
    "unsplash": {
      "id": "ouL9Ccp5KXw",
      "downloads": 14216,
      "likes": 0,
      "views": 1407002
    },
    "flickr": {
      "id": "46957274561",
      "favs": 185
    }
  },
  "plongee-en-contre-plongee": {
    "flickr": {
      "id": "31535666",
      "favs": 6
    }
  },
  "quietness": {
    "pixelfed": "7560",
    "flickr": {
      "id": "43008610425",
      "favs": 29
    }
  },
  "red-deer-in-espace-rambouillet": {
    "pixelfed": "391335136363217336",
    "flickr": {
      "id": "51645370035",
      "favs": 56
    }
  },
  "restaurant-terraces-at-night": {
    "pixelfed": "416248712115756245",
    "flickr": {
      "id": "51979745914",
      "favs": 43
    }
  },
  "resting-red-deer-in-espace-rambouillet": {
    "pixelfed": "391335404457210316",
    "flickr": {
      "id": "51644515306",
      "favs": 145
    }
  },
  "ripe": {
    "unsplash": {
      "id": "sOgCGNT3xks",
      "downloads": 5507,
      "likes": 0,
      "views": 841907
    },
    "flickr": {
      "id": "28176838603",
      "favs": 67
    }
  },
  "setting-sun-on-chambord": {
    "pixelfed": "358301728787876823",
    "flickr": {
      "id": "51622720788",
      "favs": 115
    }
  },
  "silvery-cheeked-hornbill-couple": {
    "pixelfed": "309342295579299840",
    "flickr": {
      "id": "51022199951",
      "favs": 81
    }
  },
  "smoke-shapes": {
    "unsplash": {
      "id": "qvS1EArlHIw",
      "downloads": 917,
      "likes": 0,
      "views": 100226
    },
    "flickr": {
      "id": "50432944353",
      "favs": 22
    }
  },
  "so-you-re-still-ok-for-this": {
    "pixelfed": "319854465844908032",
    "flickr": {
      "id": "50666889438",
      "favs": 84
    }
  },
  "splash": {
    "unsplash": {
      "id": "wbTiiFqEaHA",
      "downloads": 736,
      "likes": 0,
      "views": 100266
    },
    "flickr": {
      "id": "34599265232",
      "favs": 64
    }
  },
  "strobe": {
    "unsplash": {
      "id": "TVhGS6YhG_g",
      "downloads": 1241,
      "likes": 0,
      "views": 210392
    },
    "flickr": {
      "id": "51332549089",
      "favs": 202
    }
  },
  "sunset-on-lake-nakuru-s-flooded-trees": {
    "locationscout": "kenya/34385-dead-trees-lake-nakuru/80558",
    "flickr": {
      "id": "50686975421",
      "favs": 303
    }
  },
  "svetitskhoveli-cathedral": {
    "pixelfed": "441977634085791931",
    "flickr": {
      "id": "51970528072",
      "favs": 77
    }
  },
  "sweet-colors": {
    "pixelfed": "399341362122947053",
    "flickr": {
      "id": "51884834445",
      "favs": 94
    }
  },
  "tbilisi-sulfur-baths": {
    "pixelfed": "408019443239311407",
    "flickr": {
      "id": "51903608116",
      "favs": 25
    }
  },
  "the-blacksmith": {
    "unsplash": {
      "id": "2MuZ23gkFKo",
      "downloads": 16578,
      "likes": 0,
      "views": 2683357
    },
    "flickr": {
      "id": "24680290568",
      "favs": 437
    }
  },
  "the-flowering-of-the-carnations": {
    "unsplash": {
      "id": "eDsVCQNOZSM",
      "downloads": 936,
      "likes": 0,
      "views": 536291
    },
    "flickr": {
      "id": "35269644666",
      "favs": 48
    }
  },
  "the-hong-kong-symphony-of-lights-from-the-peak": {
    "locationscout": "hong-kong/1578-the-peak-tower-above-hong-kong/2662",
    "flickr": {
      "id": "20578804632",
      "favs": 97
    }
  },
  "the-iconic-acacia-tree-in-front-of-mount-kilimanjaro": {
    "pixelfed": "285156496357068800",
    "flickr": {
      "id": "51096570114",
      "favs": 510
    }
  },
  "the-mirror": {
    "locationscout": "netherlands/522-open-air-museum/919",
    "flickr": {
      "id": "17133928795",
      "favs": 164
    }
  },
  "the-path-of-light": {
    "pixelfed": "442248551047450620",
    "flickr": {
      "id": "51972014736",
      "favs": 58
    }
  },
  "the-tour": {
    "pixelfed": "398152875604880722",
    "flickr": {
      "id": "51877877860",
      "favs": 59
    }
  },
  "the-view-over-mtskheta-from-jvari-monastery": {
    "pixelfed": "412307180335655552",
    "flickr": {
      "id": "51955750032",
      "favs": 63
    }
  },
  "the-way-of-zen": {
    "unsplash": {
      "id": "itZ6lk6ksK0",
      "downloads": 183,
      "likes": 0,
      "views": 18775
    },
    "flickr": {
      "id": "34822618971",
      "favs": 28
    }
  },
  "tone-on-tone": {
    "pixelfed": "4454",
    "flickr": {
      "id": "41990797944",
      "favs": 24
    }
  },
  "travel-dreams": {
    "unsplash": {
      "id": "EqasEQO5oZQ",
      "downloads": 258,
      "likes": 0,
      "views": 62060
    },
    "flickr": {
      "id": "50709526891",
      "favs": 40
    }
  },
  "tubes": {
    "unsplash": {
      "id": "cD8v3QR-nEk",
      "downloads": 58,
      "likes": 0,
      "views": 3795
    },
    "flickr": {
      "id": "37515893964",
      "favs": 61
    }
  },
  "uncertainty": {
    "pixelfed": "1080",
    "flickr": {
      "id": "40247629271",
      "favs": 408
    }
  },
  "what-are-you-staring-at": {
    "pixelfed": "319854689078349824",
    "flickr": {
      "id": "51110476345",
      "favs": 65
    }
  },
  "women-s-800m": {
    "flickr": {
      "id": "28286281418",
      "favs": 23
    },
    "unsplash": {
      "id": "Lno6-CxVXgo",
      "downloads": 122745,
      "likes": 0,
      "views": 9169474
    }
  },
  "zemo-kalaki": {
    "pixelfed": "416249229956422891",
    "flickr": {
      "id": "51979465761",
      "favs": 61
    }
  },
  "graphite-in-batignolles": {
    "flickr": {
      "id": "52628657291",
      "favs": 52
    }
  },
  "unic-in-batignolles": {
    "flickr": {
      "id": "52628902134",
      "favs": 95
    }
  },
  "eccentric-concentric-circles-in-carcassonne-citadel": {
    "flickr": {
      "id": "52572250850",
      "favs": 47
    }
  },
  "summer-vibes-in-mundaka": {
    "flickr": {
      "id": "52478780380",
      "favs": 25
    }
  },
  "san-sebastian-evening": {
    "flickr": {
      "id": "52476925277",
      "favs": 107
    }
  },
  "castillo-de-butron": {
    "flickr": {
      "id": "52440672315",
      "favs": 97
    }
  },
  "calcada-do-carmo": {
    "flickr": {
      "id": "52438633115",
      "favs": 181
    }
  },
  "an-evening-in-draveil-after-the-rain": {
    "flickr": {
      "id": "52418844809",
      "favs": 313
    }
  },
  "loch-tummel-from-queen-s-view": {
    "flickr": {
      "id": "52264981228",
      "favs": 281
    }
  },
  "blair-castle": {
    "flickr": {
      "id": "52264965926",
      "favs": 46
    }
  },
  "eilan-donan-and-loch-alsh": {
    "flickr": {
      "id": "52262685748",
      "favs": 81
    }
  },
  "loch-alsh": {
    "flickr": {
      "id": "52262397631",
      "favs": 49
    }
  },
  "portree-harbour": {
    "flickr": {
      "id": "52261401120",
      "favs": 30
    }
  },
  "sailing-from-mallaig-to-isle-of-skye": {
    "flickr": {
      "id": "52258691099",
      "favs": 44
    }
  },
  "traigh-beaches": {
    "flickr": {
      "id": "52255987732",
      "favs": 42
    }
  },
  "at-loch-nan-uamh-s-end": {
    "flickr": {
      "id": "52255647811",
      "favs": 55
    }
  },
  "the-devil-s-staircase": {
    "flickr": {
      "id": "52252023235",
      "favs": 85
    }
  },
  "kilchurn-castle": {
    "flickr": {
      "id": "52251304150",
      "favs": 77
    }
  },
  "loch-tulla-viewpoint": {
    "flickr": {
      "id": "52250159541",
      "favs": 86
    }
  },
  "rotterdam-cube-houses-distorted": {
    "flickr": {
      "id": "52245678879",
      "favs": 100
    }
  },
  "rotterdam-cube-houses-the-rocket": {
    "flickr": {
      "id": "52245678924",
      "favs": 78
    }
  },
  "rotterdam-cube-houses-disoriented": {
    "flickr": {
      "id": "52245393031",
      "favs": 69
    }
  },
  "rotterdam-cube-houses-the-butterfly": {
    "flickr": {
      "id": "52245393111",
      "favs": 144
    }
  },
  "diani-beach": {
    "flickr": {
      "id": "52243596123",
      "favs": 41
    }
  },
  "moroccan-women-picking-wheat": {
    "flickr": {
      "id": "52227948081",
      "favs": 196
    }
  },
  "different-means-of-locomotion": {
    "flickr": {
      "id": "52165602355",
      "favs": 52
    }
  },
  "eastern-desert-perspective": {
    "flickr": {
      "id": "52165602395",
      "favs": 31
    }
  },
  "would-you-like-some-bedouin-tea": {
    "flickr": {
      "id": "52165602470",
      "favs": 165
    }
  },
  "itbay": {
    "flickr": {
      "id": "52165352569",
      "favs": 20
    }
  },
  "warm-colors-of-rome": {
    "flickr": {
      "id": "51843083588",
      "favs": 23
    }
  },
  "ancient-gods-are-in-a-bad-mood": {
    "flickr": {
      "id": "51843084298",
      "favs": 80
    }
  },
  "the-star-ferry-in-victoria-harbour-hong-kong": {
    "flickr": {
      "id": "51811370252",
      "favs": 135
    }
  },
  "tian-tan-buddha": {
    "flickr": {
      "id": "51812329161",
      "favs": 31
    }
  },
  "chung-wui-mansion": {
    "flickr": {
      "id": "51813057985",
      "favs": 42
    }
  },
  "inoummar-agadir-s-lamine": {
    "flickr": {
      "id": "51802923967",
      "favs": 98
    }
  },
  "inoummar-agadir": {
    "flickr": {
      "id": "51803884606",
      "favs": 50
    }
  },
  "asif-oussaka": {
    "flickr": {
      "id": "51804000293",
      "favs": 54
    }
  },
  "bruce-lee": {
    "flickr": {
      "id": "51642605910",
      "favs": 58
    }
  },
  "tradition-and-modernity": {
    "flickr": {
      "id": "51642603375",
      "favs": 127
    }
  },
  "fontana-di-trevi": {
    "flickr": {
      "id": "51470979747",
      "favs": 84
    }
  },
  "il-colosseo": {
    "flickr": {
      "id": "51472684390",
      "favs": 71
    }
  },
  "not-everyone-is-asleep-yet": {
    "flickr": {
      "id": "51422038358",
      "favs": 156
    }
  },
  "bali-mynah": {
    "flickr": {
      "id": "51226015097",
      "favs": 119
    }
  },
  "long-tailed-broadbill": {
    "flickr": {
      "id": "51226935488",
      "favs": 53
    }
  },
  "the-edward-youde-aviary-in-hong-kong-park": {
    "flickr": {
      "id": "51226708281",
      "favs": 19
    }
  },
  "oddly-vintage": {
    "flickr": {
      "id": "51198034881",
      "favs": 24
    }
  },
  "a-l-epee-royale": {
    "flickr": {
      "id": "51198812034",
      "favs": 33
    }
  },
  "the-manor": {
    "flickr": {
      "id": "51197323107",
      "favs": 30
    }
  },
  "the-marne-in-joinville": {
    "flickr": {
      "id": "51196766525",
      "favs": 41
    }
  },
  "joinville": {
    "flickr": {
      "id": "51195700376",
      "favs": 111
    }
  },
  "pollination": {
    "flickr": {
      "id": "51192588624",
      "favs": 98
    }
  },
  "napoleon-s-carnation": {
    "flickr": {
      "id": "51182350492",
      "favs": 60
    }
  },
  "all-quiet-on-the-frozen-traelhavet-shore": {
    "flickr": {
      "id": "51173624195",
      "favs": 67
    }
  },
  "an-evening-on-the-traelhavet-shore": {
    "flickr": {
      "id": "51151906942",
      "favs": 130
    }
  },
  "remains-of-the-frozen-sea": {
    "flickr": {
      "id": "51151171299",
      "favs": 87
    }
  },
  "oesterskaer": {
    "flickr": {
      "id": "51150621968",
      "favs": 46
    }
  },
  "naesuddens-naturreservat": {
    "flickr": {
      "id": "51149713392",
      "favs": 30
    }
  },
  "panorama-over-traelhavet": {
    "flickr": {
      "id": "51151494805",
      "favs": 59
    }
  },
  "a-long-tailed-tit-in-sweden": {
    "flickr": {
      "id": "51137733091",
      "favs": 61
    }
  },
  "children-propelling-a-tire": {
    "flickr": {
      "id": "51135785913",
      "favs": 22
    }
  },
  "newborn-african-buffalo": {
    "flickr": {
      "id": "51135786123",
      "favs": 35
    }
  },
  "a-very-curious-vervet-monkey": {
    "flickr": {
      "id": "51135570906",
      "favs": 27
    }
  },
  "the-mau-escarpment-in-great-rift-valley": {
    "flickr": {
      "id": "51110476530",
      "favs": 19
    }
  },
  "mantled-guereza": {
    "flickr": {
      "id": "51106606429",
      "favs": 26
    }
  },
  "if-symptoms-persist-seek-medical-advice": {
    "flickr": {
      "id": "51106607409",
      "favs": 30
    }
  },
  "common-ostrich": {
    "flickr": {
      "id": "51106763108",
      "favs": 54
    }
  },
  "now-you-see-me": {
    "flickr": {
      "id": "51097295365",
      "favs": 31
    }
  },
  "hard-manual-work-in-the-fields": {
    "flickr": {
      "id": "51096570709",
      "favs": 10
    }
  },
  "at-the-school-of-life": {
    "flickr": {
      "id": "51097035023",
      "favs": 33
    }
  },
  "the-village": {
    "flickr": {
      "id": "51092544150",
      "favs": 18
    }
  },
  "the-locomotion": {
    "flickr": {
      "id": "51092544285",
      "favs": 21
    }
  },
  "follow-the-path-around": {
    "flickr": {
      "id": "51092276408",
      "favs": 46
    }
  },
  "augur-buzzard": {
    "flickr": {
      "id": "51081100327",
      "favs": 55
    }
  },
  "peaceful-cohabitation": {
    "flickr": {
      "id": "51080312028",
      "favs": 88
    }
  },
  "maasai-mara-national-reserve": {
    "flickr": {
      "id": "51078372791",
      "favs": 53
    }
  },
  "small-break-with-the-protection-of-the-shade-of-the-tree": {
    "flickr": {
      "id": "51077674038",
      "favs": 54
    }
  },
  "baglafecht-weaver": {
    "flickr": {
      "id": "51077674118",
      "favs": 98
    }
  },
  "the-typical-country-town-street": {
    "flickr": {
      "id": "51077674188",
      "favs": 78
    }
  },
  "african-baobab": {
    "flickr": {
      "id": "51077674233",
      "favs": 28
    }
  },
  "ladies": {
    "flickr": {
      "id": "51062898003",
      "favs": 15
    }
  },
  "the-apprentice": {
    "flickr": {
      "id": "51055110373",
      "favs": 103
    }
  },
  "little-home": {
    "flickr": {
      "id": "51054597433",
      "favs": 22
    }
  },
  "crowded-place": {
    "flickr": {
      "id": "51054597528",
      "favs": 54
    }
  },
  "a-little-nap": {
    "flickr": {
      "id": "51032572626",
      "favs": 16
    }
  },
  "tetris": {
    "flickr": {
      "id": "51031835258",
      "favs": 13
    }
  },
  "cleaning-the-dust": {
    "flickr": {
      "id": "51031837058",
      "favs": 29
    }
  },
  "making-fire": {
    "flickr": {
      "id": "51031839783",
      "favs": 34
    }
  },
  "the-little-one": {
    "flickr": {
      "id": "50901528012",
      "favs": 66
    }
  },
  "nothing-to-see-or-maybe": {
    "flickr": {
      "id": "50891615232",
      "favs": 26
    }
  },
  "proud-maasai": {
    "flickr": {
      "id": "50664754801",
      "favs": 170
    }
  },
  "african-fish-eagle-in-nakuru": {
    "flickr": {
      "id": "50656673521",
      "favs": 72
    }
  },
  "black-rhinoceros-in-lake-nakuru-national-park": {
    "flickr": {
      "id": "50569752712",
      "favs": 118
    }
  },
  "on-the-dirt-track-again": {
    "flickr": {
      "id": "50493684987",
      "favs": 40
    }
  },
  "spiderman-is-watching": {
    "flickr": {
      "id": "50493529496",
      "favs": 39
    }
  },
  "lappet-faced-vulture-on-a-tree-in-maasai-mara-national-reserve": {
    "flickr": {
      "id": "50450172653",
      "favs": 78
    }
  },
  "lappet-faced-vulture-in-maasai-mara-national-reserve": {
    "flickr": {
      "id": "50450879591",
      "favs": 56
    }
  },
  "close-to-me": {
    "flickr": {
      "id": "50444266878",
      "favs": 98
    }
  },
  "masai-giraffes-like-tree-leaves": {
    "flickr": {
      "id": "50440777107",
      "favs": 88
    }
  },
  "wisps-of-smoke": {
    "flickr": {
      "id": "50433806577",
      "favs": 45
    }
  },
  "young-olive-baboon-at-sunset": {
    "flickr": {
      "id": "50385984336",
      "favs": 71
    }
  },
  "a-nap-in-the-shade": {
    "flickr": {
      "id": "50091788036",
      "favs": 57
    }
  },
  "lioness-in-maasai-mara": {
    "flickr": {
      "id": "50023658177",
      "favs": 118
    }
  },
  "pied-kingfisher-in-lake-nakuru-national-park-kenya": {
    "flickr": {
      "id": "49875816887",
      "favs": 164
    }
  },
  "variable-sunbird-in-maasai-mara-national-reserve-kenya": {
    "flickr": {
      "id": "49875507711",
      "favs": 231
    }
  },
  "who-is-the-observer": {
    "flickr": {
      "id": "49834778252",
      "favs": 89
    }
  },
  "juvenile-d-arnaud-s-barbets-in-sunset": {
    "flickr": {
      "id": "49834471661",
      "favs": 235
    }
  },
  "lioness-on-the-lookout": {
    "flickr": {
      "id": "49799394586",
      "favs": 92
    }
  },
  "elephants-family-in-maasai-mara": {
    "flickr": {
      "id": "49799394771",
      "favs": 189
    }
  },
  "juvenile-european-roller-in-africa": {
    "flickr": {
      "id": "49765703513",
      "favs": 126
    }
  },
  "on-the-move": {
    "flickr": {
      "id": "49765135981",
      "favs": 266
    }
  },
  "civilization": {
    "flickr": {
      "id": "49765137101",
      "favs": 45
    }
  },
  "what-are-you-waiting-for": {
    "flickr": {
      "id": "49765464987",
      "favs": 38
    }
  },
  "alone": {
    "flickr": {
      "id": "49764608963",
      "favs": 75
    }
  },
  "40-c-no-problem": {
    "flickr": {
      "id": "49765142876",
      "favs": 6
    }
  },
  "african-fish-eagle": {
    "flickr": {
      "id": "49474587311",
      "favs": 76
    }
  },
  "staying-close": {
    "flickr": {
      "id": "49420483153",
      "favs": 115
    }
  },
  "grant-s-zebras": {
    "flickr": {
      "id": "49205289203",
      "favs": 56
    }
  },
  "morning-stroll": {
    "flickr": {
      "id": "49190084601",
      "favs": 236
    }
  },
  "empty": {
    "flickr": {
      "id": "49182551498",
      "favs": 68
    }
  },
  "elephants-at-sunrise-in-front-of-kilimanjaro": {
    "flickr": {
      "id": "49076005902",
      "favs": 347
    }
  },
  "red-legged-golden-orb-weaver-spider": {
    "flickr": {
      "id": "49034841588",
      "favs": 96
    }
  },
  "here-comes-the-secretary": {
    "flickr": {
      "id": "49030302163",
      "favs": 48
    }
  },
  "don-t-be-afraid-i-m-just-yawning": {
    "flickr": {
      "id": "49030809111",
      "favs": 49
    }
  },
  "flamingos-wading-in-wetlands-in-amboseli-national-park": {
    "flickr": {
      "id": "48931945056",
      "favs": 89
    }
  },
  "saddle-billed-stork": {
    "flickr": {
      "id": "48930610796",
      "favs": 76
    }
  },
  "waiting-for-dusk": {
    "flickr": {
      "id": "48775168158",
      "favs": 82
    }
  },
  "the-snows-of-kilimanjaro": {
    "flickr": {
      "id": "48756318257",
      "favs": 171
    }
  },
  "north-collateral-of-the-cathedral-of-notre-dame-de-reims": {
    "flickr": {
      "id": "33855819088",
      "favs": 78
    }
  },
  "after-the-rain": {
    "flickr": {
      "id": "45637011424",
      "favs": 281
    }
  },
  "little-drizzle": {
    "flickr": {
      "id": "45431850335",
      "favs": 278
    }
  },
  "great-spotted-woodpecker": {
    "flickr": {
      "id": "45470933964",
      "favs": 31
    }
  },
  "toucan-toco": {
    "flickr": {
      "id": "45239379565",
      "favs": 108
    }
  },
  "superb-starling": {
    "flickr": {
      "id": "45223966685",
      "favs": 102
    }
  },
  "lesser-blue-eared-starling": {
    "flickr": {
      "id": "45223966915",
      "favs": 61
    }
  },
  "ploumanac-h-b-and-w": {
    "flickr": {
      "id": "44901288605",
      "favs": 227
    }
  },
  "dave-holland-and-prism-at-blue-note-jazz-club": {
    "flickr": {
      "id": "43970978360",
      "favs": 34
    }
  },
  "down-to-the-sky": {
    "flickr": {
      "id": "43934706401",
      "favs": 40
    }
  },
  "ponte-sant-angelo": {
    "flickr": {
      "id": "28832614787",
      "favs": 203
    }
  },
  "an-evening-on-top-of-rome": {
    "flickr": {
      "id": "29645299478",
      "favs": 61
    }
  },
  "hoarding-disorder": {
    "flickr": {
      "id": "27953015007",
      "favs": 117
    }
  },
  "primary-colours-of-burano": {
    "flickr": {
      "id": "40402950270",
      "favs": 16
    }
  },
  "colourful-burano": {
    "flickr": {
      "id": "28337241078",
      "favs": 22
    }
  },
  "a-peaceful-canal-in-venice": {
    "flickr": {
      "id": "28337241198",
      "favs": 28
    }
  },
  "mosquito": {
    "flickr": {
      "id": "40391218190",
      "favs": 58
    }
  },
  "le-galatee-sans-voie-lactee": {
    "flickr": {
      "id": "39751142141",
      "favs": 38
    }
  },
  "wet-bee-after-the-rain": {
    "flickr": {
      "id": "38194699825",
      "favs": 31
    }
  },
  "the-violinist": {
    "flickr": {
      "id": "38196814766",
      "favs": 51
    }
  },
  "saint-pancras": {
    "flickr": {
      "id": "37770707706",
      "favs": 22
    }
  },
  "muscles": {
    "flickr": {
      "id": "36901577156",
      "favs": 43
    }
  },
  "the-fishmonger": {
    "flickr": {
      "id": "36661770050",
      "favs": 32
    }
  },
  "blue-is-the-warmest-colour": {
    "flickr": {
      "id": "36251088593",
      "favs": 56
    }
  },
  "ploumanac-h": {
    "flickr": {
      "id": "36074514041",
      "favs": 129
    }
  },
  "the-many-faces-of-iron-man": {
    "flickr": {
      "id": "35375323676",
      "favs": 18
    }
  },
  "the-moroccan-high-atlas": {
    "flickr": {
      "id": "34940936111",
      "favs": 46
    }
  },
  "belgian-pride": {
    "flickr": {
      "id": "34776202281",
      "favs": 49
    }
  },
  "menace": {
    "flickr": {
      "id": "34774194165",
      "favs": 48
    }
  },
  "look-at-me-in-the-eye": {
    "flickr": {
      "id": "33840803976",
      "favs": 38
    }
  },
  "along-the-shore": {
    "flickr": {
      "id": "33724443262",
      "favs": 57
    }
  },
  "aux-couleurs-modernes": {
    "flickr": {
      "id": "32859758334",
      "favs": 26
    }
  },
  "lower-manhattan-b-and-w-edition": {
    "flickr": {
      "id": "32718697703",
      "favs": 52
    }
  },
  "laherez": {
    "flickr": {
      "id": "31837133614",
      "favs": 57
    }
  },
  "whatever-we-do-to-the-web-of-life-we-do-to-ourselves": {
    "flickr": {
      "id": "32456359616",
      "favs": 50
    }
  },
  "the-new-road-to-hell-s-kitchen": {
    "flickr": {
      "id": "32217211525",
      "favs": 23
    }
  },
  "primary-colors": {
    "flickr": {
      "id": "31295581352",
      "favs": 8
    }
  },
  "le-guilvinec-by-night": {
    "flickr": {
      "id": "30819396815",
      "favs": 42
    }
  },
  "the-city-that-never-sleeps": {
    "flickr": {
      "id": "29825708714",
      "favs": 19
    }
  },
  "rua-vitor-cordon": {
    "flickr": {
      "id": "30347234535",
      "favs": 12
    }
  },
  "looking-up": {
    "flickr": {
      "id": "30239789831",
      "favs": 11
    }
  },
  "liberty-has-been-framed": {
    "flickr": {
      "id": "29199916065",
      "favs": 63
    }
  },
  "a-bridge-not-so-far": {
    "flickr": {
      "id": "28304272563",
      "favs": 79
    }
  },
  "aurelien": {
    "flickr": {
      "id": "24228537543",
      "favs": 216
    }
  },
  "curves": {
    "flickr": {
      "id": "24650336026",
      "favs": 15
    }
  },
  "did-i-go-over-the-top": {
    "flickr": {
      "id": "21467099176",
      "favs": 55
    }
  },
  "portree": {
    "flickr": {
      "id": "21339174966",
      "favs": 23
    }
  },
  "breathtaking-brooklyn-bridge-night-panorama": {
    "flickr": {
      "id": "21145812810",
      "favs": 287
    }
  },
  "ploumanac-h-lighthouse": {
    "flickr": {
      "id": "21304908075",
      "favs": 76
    }
  },
  "lower-manhattan": {
    "flickr": {
      "id": "20985227328",
      "favs": 145
    }
  },
  "colorful-edges": {
    "flickr": {
      "id": "16145538197",
      "favs": 7
    }
  },
  "follow-the-rythm": {
    "flickr": {
      "id": "16213387835",
      "favs": 2
    }
  },
  "winter-is-coming": {
    "flickr": {
      "id": "15728669622",
      "favs": 22
    }
  },
  "aka-hadoken": {
    "flickr": {
      "id": "14648980519",
      "favs": 103
    }
  },
  "prendre-un-enfant-par-la-main": {
    "flickr": {
      "id": "14681931111",
      "favs": 54
    }
  },
  "leslie": {
    "flickr": {
      "id": "14420719279",
      "favs": 419
    }
  },
  "zen": {
    "flickr": {
      "id": "14464376335",
      "favs": 27
    }
  },
  "limitless": {
    "flickr": {
      "id": "14453427844",
      "favs": 13
    }
  },
  "layered-symmetry": {
    "flickr": {
      "id": "13601977205",
      "favs": 22
    }
  },
  "sakura": {
    "flickr": {
      "id": "12915637465",
      "favs": 62
    }
  },
  "winter": {
    "flickr": {
      "id": "12842257345",
      "favs": 7
    }
  },
  "le-roof": {
    "flickr": {
      "id": "8653513362",
      "favs": 15
    }
  },
  "butterfly": {
    "flickr": {
      "id": "8291458603",
      "favs": 3
    }
  },
  "first-snow-at-sunset": {
    "flickr": {
      "id": "8285153636",
      "favs": 16
    }
  },
  "welcome": {
    "flickr": {
      "id": "4087018359",
      "favs": 5
    }
  },
  "mud-lover": {
    "flickr": {
      "id": "3506857120",
      "favs": 11
    }
  },
  "zig-zag": {
    "flickr": {
      "id": "3242673078",
      "favs": 9
    }
  },
  "stairz": {
    "flickr": {
      "id": "3241829519",
      "favs": 69
    }
  },
  "having-fun": {
    "flickr": {
      "id": "128295466",
      "favs": 9
    }
  },
  "lost-in-white-space": {
    "flickr": {
      "id": "10566776",
      "favs": 29
    }
  },
  "far-west-cowboys-from-the-movies": {
    "flickr": {
      "id": "3922674",
      "favs": 33
    }
  },
  "the-arch-from-once-upon-a-time-in-the-west-in-texas-hollywood": {
    "flickr": {
      "id": "3922589",
      "favs": 21
    }
  },
  "the-plaza-de-toros-de-ronda": {
    "flickr": {
      "id": "3478629",
      "favs": 7
    }
  },
  "the-walls-of-the-alcazar-of-seville": {
    "flickr": {
      "id": "3478428",
      "favs": 6
    }
  },
  "wood-pier-in-sunset": {
    "flickr": {
      "id": "3057330",
      "favs": 27
    }
  },
  "split-level-photography": {
    "flickr": {
      "id": "3057318",
      "favs": 10
    }
  },
  "while-waiting": {
    "flickr": {
      "id": "15104205129",
      "favs": 410
    }
  },
  "dreamer": {
    "flickr": {
      "id": "14350284830",
      "favs": 236
    }
  },
  "in-all-its-simplicity": {
    "flickr": {
      "id": "14486876234",
      "favs": 239
    }
  },
  "mangrove-tree-in-south-new-caledonia": {
    "flickr": {
      "id": "9255433378",
      "favs": 7
    }
  },
  "brussels": {
    "flickr": {
      "id": "3295418597",
      "favs": 16
    }
  },
  "scarlet-lily-beetle": {
    "flickr": {
      "id": "3211000164",
      "favs": 6
    }
  },
  "rusty": {
    "flickr": {
      "id": "3117915830",
      "favs": 36
    }
  },
  "harvesting-on-bluebells": {
    "flickr": {
      "id": "3101454144",
      "favs": 6
    }
  },
  "colourful-window-in-burano": {
    "flickr": {
      "id": "2459061166",
      "favs": 25
    }
  },
  "another-colourful-window-in-burano": {
    "flickr": {
      "id": "2459060966",
      "favs": 18
    }
  },
  "waiting-for-the-high-tide": {
    "flickr": {
      "id": "45382472592",
      "favs": 75
    }
  },
  "the-demoiselle-after-the-shower": {
    "flickr": {
      "id": "44747293171",
      "favs": 36
    }
  },
  "defenseless": {
    "flickr": {
      "id": "42066011894",
      "favs": 338
    }
  },
  "v-j-day-in-times-square-kobra-s-colorful-edition": {
    "flickr": {
      "id": "41236577805",
      "favs": 28
    }
  },
  "the-threat": {
    "flickr": {
      "id": "27455447408",
      "favs": 32
    }
  },
  "one-hope": {
    "flickr": {
      "id": "38632965290",
      "favs": 368
    }
  },
  "up-to-your-neck-in-water": {
    "flickr": {
      "id": "26414370488",
      "favs": 74
    }
  },
  "fog-over-niort": {
    "flickr": {
      "id": "27145092159",
      "favs": 84
    }
  },
  "a-nut-shell-in-etretat": {
    "flickr": {
      "id": "26667324569",
      "favs": 39
    }
  },
  "a-riad-in-taroudant-morocco": {
    "flickr": {
      "id": "37708512224",
      "favs": 30
    }
  },
  "aurelien-b-and-w": {
    "flickr": {
      "id": "37967866012",
      "favs": 133
    }
  },
  "egret-at-sunset": {
    "flickr": {
      "id": "33678234233",
      "favs": 32
    }
  },
  "japanese-zen": {
    "flickr": {
      "id": "32707361945",
      "favs": 52
    }
  },
  "kiss": {
    "flickr": {
      "id": "4347437332",
      "favs": 101
    }
  },
  "larva-of-tenthredo-marginella": {
    "flickr": {
      "id": "3281342129",
      "favs": 4
    }
  },
  "makeshift-telephoto-lens": {
    "flickr": {
      "id": "52866743781",
      "favs": 24
    }
  },
  "fahrenheit-451": {
    "flickr": {
      "id": "52867186218",
      "favs": 16
    }
  },
  "the-walking-dead-bloodstains": {
    "flickr": {
      "id": "52861533766",
      "favs": 23
    }
  },
  "around-the-world-in-80-seconds": {
    "flickr": {
      "id": "52859919404",
      "favs": 27
    }
  },
  "shy-scarlet-macaw": {
    "flickr": {
      "id": "52934218662",
      "favs": 53
    }
  },
  "scarlet-ibis": {
    "flickr": {
      "id": "52933977907",
      "favs": 30
    }
  },
  "blue-and-yellow-macaw": {
    "flickr": {
      "id": "52934729244",
      "favs": 17
    }
  },
  "colorful-feathers": {
    "flickr": {
      "id": "52934572286",
      "favs": 11
    }
  },
  "coco": {
    "flickr": {
      "id": "52933974592",
      "favs": 10
    }
  },
  "le-gratin-mondain-in-noyers-sur-serein": {
    "flickr": {
      "id": "52973224113",
      "favs": 0
    }
  }
}